{"id":"INV-4277404E-0EB","shopId":"SHOP-FF87CB61","drugId":"DRG-D37E6E4B","totalStock":300,"shopFloorStock":50,"storageStock":250,"reservedStock":0,"quarantinedStock":0,"reorderPoint":50,"storageLocation":"Shelf A-1","batches":[{"batchNumber":"BATCH-E2E-PRIME","supplierId":"SUP-871E50A4","quantityOnHand":150,"receivedDate":"2026-05-08T07:55:41.592101Z","expiryDate":"2028-05-01T00:00:00Z","purchasePrice":4.00,"sellingPrice":12.00,"status":"Active","location":"Storage","storageLocation":""},{"batchNumber":"BATCH-E2E-PO-001","supplierId":"SUP-871E50A4","quantityOnHand":100,"receivedDate":"2026-05-08T07:56:12.5088308Z","expiryDate":"2028-06-01T00:00:00Z","purchasePrice":4.00,"sellingPrice":12.00,"status":"Active","location":"Storage","storageLocation":"Shelf A-1"},{"batchNumber":"BATCH-E2E-PRIME","supplierId":"SUP-871E50A4","quantityOnHand":50,"receivedDate":"2026-05-08T07:55:41.592101Z","expiryDate":"2028-05-01T00:00:00Z","purchasePrice":4.00,"sellingPrice":12.00,"status":"Active","location":"ShopFloor","storageLocation":"Shop Floor"}],"shopPricing":{"costPrice":4.00,"sellingPrice":12.00,"discount":0.00,"currency":"USD","taxRate":0.00,"profitMargin":8.0000,"profitMarginPercentage":200.00,"lastPriceUpdate":"2026-05-08T07:55:41.59208Z","packagingLevelPrices":{}},"packaging":null,"isAvailable":true,"lastRestockDate":"2026-05-08T07:56:12.508842Z","createdAt":"2026-05-08T07:55:41.592098Z","updatedAt":"2026-05-08T07:57:00.0749397Z"}